Metadata-Version: 1.0
Name: python-speak
Version: 0.0.1
Summary: python speak,You can use it to convert text into speech
Home-page: UNKNOWN
Author: 轩轩
Author-email: 3603695237@qq.com
License: UNKNOWN
Platform: UNKNOWN
